README.md
setup.py
modules/__init__.py
modules/__main__.py
modules/__version__.py
modules/common.py
modules/timemate.py
timemate.egg-info/PKG-INFO
timemate.egg-info/SOURCES.txt
timemate.egg-info/dependency_links.txt
timemate.egg-info/entry_points.txt
timemate.egg-info/requires.txt
timemate.egg-info/top_level.txt