Metadata-Version: 2.1
Name: timemate
Version: 0.0.24
Summary: Record and report times spent in various activities.
Home-page: https://github.com/dagraham/timemate
Author: Daniel A Graham
Author-email: dnlgrhm@gmail.com
Requires-Python: >=3.9
Requires-Dist: click
Requires-Dist: click-shell
Requires-Dist: prompt_toolkit
Requires-Dist: python-dateutil
Requires-Dist: rich
Requires-Dist: pyyaml
